automodeling/__init__.py
automodeling/base.py
automodeling/ensemble.py
automodeling/linear_model.py
automodeling/svm.py
auto_modeling-0.2.0.dist-info/LICENSE
auto_modeling-0.2.0.dist-info/METADATA
auto_modeling-0.2.0.dist-info/WHEEL
auto_modeling-0.2.0.dist-info/top_level.txt
auto_modeling-0.2.0.dist-info/RECORD
