Metadata-Version: 2.1
Name: auto-modeling
Version: 0.2.0
Summary: Automated model selection and optimization using scikit-learn and Optuna
Author-email: Cristóbal Torres Rojas <ctorres.ai@hotmail.com>
Requires-Python: >=3.8
License-File: LICENSE
Requires-Dist: scikit-learn>=1.3.2
Requires-Dist: optuna>=4.3.0
